{
      "item_icecream_name": "Ледяное мороженое",
      "item_icecream_desc": "Настолько холодное, что ощущение, будто можно пройти сквозь огонь.",
      "item_icecream_effecttooltip": "Вам так холодно, что прогулка по огню на самом деле звучит хорошо.",
      "item_icecream_effectstartmessage": "Ваши губы посинели.",
      "item_burger_name": "Бургер",
      "item_burger_desc": "Немного этого и немного того, положите это на булочку и считайте, что все готово!",
      "item_moochi_name": "Моти",
      "item_moochi_desc": "Время моти!",
      "item_electriccreamcone_name": "Электрическое мороженое",
      "item_electriccreamcon_desc": "Оно разбудит вас, придаст бодрости для вашего путешествия и убьет любое воздействие яда.",
      "item_electriccreamcone_effecttooltip": "Вы чувствуете себя невероятно устойчивым к ядам.",
      "item_electriccreamcone_effectstartmessage": "Вы шокированы",
      "item_chickenfriedlox_name": "Жареный быкоящер с курицей",
      "item_chickenfriedlox_desc": "Знаешь, мне нравится жареный цыпленок... То есть жареный быкоящер с курицей.",
      "item_glazedcarrots_name": "Глазированная морковь",
      "item_glazedcarrots_desc": "В чём дело, док?",
      "item_jimmyspbj_name": "Бутерброд с арахисовым маслом и джемом",
      "item_jimmyspbj_desc": "Любимец каждого юного викинга!",
      "item_fishstew_name": "Рыбное рагу",
      "item_fishstew_desc": "Вкусное рыбное рагу.",
      "item_pizza_name": "Пицца",
      "item_pizza_desc": "У нас должна быть вся начинка, чтобы добавить её на лепешку.",
      "item_rawpork_name": "Сырая свинина",
      "item_rawpork_desc": "Это сырая свинина, кто бы мог подумать?",
      "item_tastymead_name": "Вкусная медовуха",
      "item_tastymead_desc": "Что означает это свечение? Хорошая штука!",
      "item_candiedturnips_name": "Засахаренная репа",
      "item_candiedturnips_desc": "Кто не любит хороший десерт викингов?",
      "item_rksbirthdaycake_name": "Праздничный торт",
      "item_rksbirthdaycake_desc": "Наслаждайтесь тортом в честь дня рождения!",
      "item_porkrind_name": "Свиные шкварки",
      "item_porkrind_desc": "Они обжаренные, ЧТО вы об этом думаете?!",
      "item_carrotbutter_name": "Морковное масло",
      "item_carrotbutter_desc": "Необходимое дополнение ко многим блюдам.",
      "item_acidcream_name": "Кислотное мороженое",
      "item_acidcream_desc": "Подождите, ЧТО в нем находится?",
      "item_acidcream_effecttooltip": "Вы только что съели cлизь, теперь вы думаете, что ничто не может шокировать вас.",
      "item_acidcream_effectstartmessage": "Вы чувствуете себя зеленым",
      "item_porridge_name": "Овсяная каша",
      "item_porridge_desc": "Не слишком горячая, не слишком холодная, каша в самый раз!",
      "item_boiledegg_name": "Вареное яйцо",
      "item_boiledegg_desc": "Маленькое яйцо, которое вы найдете в гнезде, возможно, вы сможете пронести его через портал..",
      "item_egg_name": "Яйцо чайки",
      "item_egg_desc": "Маленькое синее яйцо чайки.",
      "item_bacon_name": "Бекон",
      "item_bacon_desc": "Этот бекон сведет тебя с ума!",
      "item_kebab_name": "Кебаб",
      "item_kebab_desc": "Приятного аппетита добрый Викинг!",
      "item_bloodsausage_name": "Кровяная колбаса",
      "item_bloodsausage_desc": "Что есть лучше колбасы? Кровяная колбаса!",
      "item_drakeegg_name": "Яйцо дракона",
      "item_drakeegg_desc": "Гораздо меньшего размера яйцо, которое вы найдете в гнезде, может быть, вы сможете перенести его через портал.",
      "item_omlette_name": "Омлет",
      "item_omlette_desc": "Полезный вкусный омлет",
      "item_firecream_name": "Огненное мороженое",
      "item_firecream_desc": "Призрачный перец, ничего не имею против этой жгучести. Вы готовы стать поджигателем?",
      "item_firecream_effecttooltip": "Что это за запах? Вы горите!?!?",
      "item_firecream_effectstartmessage": "Оно горит!",
      "item_broth_name": "Бульон",
      "item_broth_desc": "Костный... бульон, отличная основа для супов или тушеного мяса.",
      "item_spicedlatte_name": "Латте со специями",
      "item_spicedlatte_desc": "Особый напиток для весьма особенного викинга!",
      "item_hagis_name": "Хаггис",
      "item_hagis_desc": "Баранье потроха, порубленные с морковью и репой в бараньем желудке",
      "item_pancakes_name": "Панкейк",
      "item_pancakes_desc": "Традиционное блюдо на завтрак.",
      "item_carrotsticks_name": "Морковные палочки",
      "item_carrotsticks_desc": "В чём дело, док?",
      "item_coffee_name": "Кофе",
      "item_coffee_desc": "Как ни говори кофе всегда вкусное.",
      "item_nut-ella_name": "Нутелла",
      "item_nut-ella_desc": "Вкусно на всём!",
      "item_chefshat_name": "Шапка шеф-повара",
      "item_chefshat_desc": "Повышает получаемый опыт для навыка кулинарии.",
      "item_smokedfish_name": "Копченая рыба",
      "item_smokedfish_desc": "Сюда рыбка, рыбка, рыбка! Запрыгивай сейчас в мою коптильню, пожалуйста.",
      "item_grill_name": "Гриль",
      "item_smokelessbrazier_name": "Бездымный мангал",
      "item_smokelessfirepit_name": "Бездымный костер",
      "item_stonegriddle_name": "Каменный гридль",
      "item_smokelesshearth_name": "Бездымный очаг",
      "item_oven_name": "Печь",
      "item_oven_desc": "$item_oven_name $piece_upgrade",
      "item_preptable_name": "Стол для готовки",
      "skill_gore-mand_name": "Кулинария",
      "skill_gore-mand_desc": "Научитесь готовить и есть как викинг!",
      "effect_cookingbonus_name": "Кулинарный бонус",
      "effect_cookingbonus_message1": "Никто не рождается отличным поваром, каждый учится собственных ошибках. - Джулия Чайлд", 
      "effect_cookingbonus_message2": "Вам не нужно готовить причудливые или сложные шедевры, просто вкусная еда из свежих продуктов.. - Джулия Чайлд", 
      "effect_cookingbonus_message3": "Люди, которые любят поесть, всегда являются хорошими людьми.. - Джулия Чайлд",
      "effect_cookingbonus_message4": "Хорошо готовить, не тоже самое что готовить изысканно. - Джулия Чайлд", 
      "effect_cookingbonus_message5": "Единственный раз, когда нужно есть диетическую пищу, это когда вы ждете, пока приготовится стейк. - Джулия Чайлд", 
      "effect_cookingbonus_message6": "Пока я не открыла для себя кулинарию, я никогда ничем по-настоящему не интересовалась. - Джулия Чайлд", 
      "effect_cookingbonus_message7": "Вы масло для моего хлеба и воздух для моей жизни. - Джулия Чайлд",
      "effect_cookingbonus_message8": "Жир придает блюду аромат. - Джулия Чайлд", 
      "effect_cookingbonus_message9": "Если вы боитесь масла, используйте сливки. - Джулия Чайлд", 
      "effect_cookingbonus_message10": "Мне было 32 года, когда я начала готовить, до тех пор я просто ела. - Джулия Чайлд", 
      "effect_cookingbonus_message11": "Вечеринка без торта, это просто собрание. - Джулия Чайлд", 
      "effect_cookingbonus_message12": "Единственный реальный камень преткновения, это страх неудачи. В кулинарии у вас должно быть отношение как \"какого черта\". - Джулия Чайлд", 
      "effect_cookingbonus_message13": "Во Франции кулинария - это серьезное искусство и национальный вид спорта. - Джулия Чайлд", 
      "effect_cookingbonus_message14": "Вы ХОЗЯИН этого теста. - Джулия Чайлд", 
      "effect_cookingbonus_message15": "С достаточным количеством масла все будет в пользу. - Джулия Чайлд", 
      "effect_cookingbonus_message16": "Обычно чья-то стряпня лучше, чем вы думаете. - Джулия Чайлд",
      "jotunn_modsettings": "Настройки модов"
  }
